RLTest/Enterprise/CcsMock.py
RLTest/Enterprise/Dmc.py
RLTest/Enterprise/EnterpriseClusterEnv.py
RLTest/Enterprise/__init__.py
RLTest/Enterprise/binaryrepo.py
RLTest/__init__.py
RLTest/__main__.py
RLTest/_version.py
RLTest/debuggers.py
RLTest/env.py
RLTest/exists_redis.py
RLTest/loader.py
RLTest/random_port.py
RLTest/redis_cluster.py
RLTest/redis_enterprise_cluster.py
RLTest/redis_std.py
RLTest/utils.py
rltest-0.7.20.dist-info/METADATA
rltest-0.7.20.dist-info/WHEEL
rltest-0.7.20.dist-info/entry_points.txt
rltest-0.7.20.dist-info/licenses/LICENSE
rltest-0.7.20.dist-info/RECORD
